{"name":"SOMA Network Testnet","network_type":"eip155","chain_id":"2323","symbol":"tSMA","native_asset":null,"decimals":18,"rpc_urls":["https://data-testnet-v1.somanetwork.io","https://block-testnet-v1.somanetwork.io","https://testnet-au-server-2.somanetwork.io","https://testnet-au-server-1.somanetwork.io","https://testnet-sg-server-1.somanetwork.io","https://testnet-sg-server-2.somanetwork.io"],"selected_rpc_url":0,"explorers":[{"name":"SOMA Testnet Explorer","url":"https://testnet.somascan.io","explorer_type":"eip3091"}],"selected_explorer":0,"slip44":1,"icon":null}